rgb2hex/__init__.py
rgb2hex/main.py
rgb2hex-0.1.0.dist-info/LICENCE
rgb2hex-0.1.0.dist-info/METADATA
rgb2hex-0.1.0.dist-info/WHEEL
rgb2hex-0.1.0.dist-info/top_level.txt
rgb2hex-0.1.0.dist-info/RECORD
