Metadata-Version: 2.1
Name: rgb2hex
Version: 0.1.0
Summary: A simple Python library for converting between Hexadecimal and RGB color formats
Home-page: https://github.com/webtechmoz/rgb2hex.git
Author: Web Tech Moz
Author-email: zoidycine@gmail.com
License: MIT
Keywords: hex2rgb,rgb2hex,rgbtohexadecimal,hex-to-rgb,rgbhex
Classifier: Programming Language :: Python :: 3.10
Classifier: License :: OSI Approved :: MIT License
Classifier: Operating System :: OS Independent
Requires-Python: >=3.10
License-File: LICENCE
